JiucaiDeZiwoXiuyangFix1/README.md
JiucaiDeZiwoXiuyangFix1/__init__.py
JiucaiDeZiwoXiuyangFix1/__main__.py
JiucaiDeZiwoXiuyangFix1/file.epub
JiucaiDeZiwoXiuyangFix1/index.html
JiucaiDeZiwoXiuyangFix1/css/__init__.py
JiucaiDeZiwoXiuyangFix1/css/annotations.css
JiucaiDeZiwoXiuyangFix1/css/main.css
JiucaiDeZiwoXiuyangFix1/css/normalize.css
JiucaiDeZiwoXiuyangFix1/css/popup.css
JiucaiDeZiwoXiuyangFix1/font/__init__.py
JiucaiDeZiwoXiuyangFix1/font/fontello.eot
JiucaiDeZiwoXiuyangFix1/font/fontello.svg
JiucaiDeZiwoXiuyangFix1/font/fontello.ttf
JiucaiDeZiwoXiuyangFix1/font/fontello.woff
JiucaiDeZiwoXiuyangFix1/img/__init__.py
JiucaiDeZiwoXiuyangFix1/img/annotator-glyph-sprite.png
JiucaiDeZiwoXiuyangFix1/img/annotator-icon-sprite.png
JiucaiDeZiwoXiuyangFix1/img/apple-touch-icon.png
JiucaiDeZiwoXiuyangFix1/img/cancelfullscreen.png
JiucaiDeZiwoXiuyangFix1/img/close.png
JiucaiDeZiwoXiuyangFix1/img/fullscreen.png
JiucaiDeZiwoXiuyangFix1/img/loader.gif
JiucaiDeZiwoXiuyangFix1/img/menu-icon.png
JiucaiDeZiwoXiuyangFix1/img/save.png
JiucaiDeZiwoXiuyangFix1/img/saved.png
JiucaiDeZiwoXiuyangFix1/img/settings-s.png
JiucaiDeZiwoXiuyangFix1/img/settings.png
JiucaiDeZiwoXiuyangFix1/img/star.png
JiucaiDeZiwoXiuyangFix1/js/__init__.py
JiucaiDeZiwoXiuyangFix1/js/epub.js
JiucaiDeZiwoXiuyangFix1/js/epub.min.js
JiucaiDeZiwoXiuyangFix1/js/epub.min.map
JiucaiDeZiwoXiuyangFix1/js/hooks.min.js
JiucaiDeZiwoXiuyangFix1/js/hooks.min.map
JiucaiDeZiwoXiuyangFix1/js/reader.js
JiucaiDeZiwoXiuyangFix1/js/reader.js.map
JiucaiDeZiwoXiuyangFix1/js/reader.min.js
JiucaiDeZiwoXiuyangFix1/js/reader.min.map
JiucaiDeZiwoXiuyangFix1/js/hooks/__init__.py
JiucaiDeZiwoXiuyangFix1/js/hooks/extensions/__init__.py
JiucaiDeZiwoXiuyangFix1/js/hooks/extensions/highlight.js
JiucaiDeZiwoXiuyangFix1/js/libs/__init__.py
JiucaiDeZiwoXiuyangFix1/js/libs/jquery.min.js
JiucaiDeZiwoXiuyangFix1/js/libs/localforage.min.js
JiucaiDeZiwoXiuyangFix1/js/libs/screenfull.js
JiucaiDeZiwoXiuyangFix1/js/libs/screenfull.min.js
jiucai_de_ziwo_xiuyang_fix1-2025.3.24.0.dist-info/METADATA
jiucai_de_ziwo_xiuyang_fix1-2025.3.24.0.dist-info/WHEEL
jiucai_de_ziwo_xiuyang_fix1-2025.3.24.0.dist-info/entry_points.txt
jiucai_de_ziwo_xiuyang_fix1-2025.3.24.0.dist-info/top_level.txt
jiucai_de_ziwo_xiuyang_fix1-2025.3.24.0.dist-info/RECORD
